{"date":"2017-09-30","time":"16:00","venue":"Chinmaya Niketan, Norcross","detail":"Sri. Vignesh Ishwar is a senior disciple of Sri T. M. Krishna","artists":[{"name":"Vignesh Ishwar","instrument":"Vocal"},{"name":"L. Ramakrishnan","instrument":"Violin"},{"name":"Akshay Anantapadmanabhan","instrument":"Mridangam"},{"name":"K. V. Gopalakrishnan","instrument":"Kanchira"}],"photos":[{"src":"vignesh-ishwar.jpg","title":"vignesh-ishwar"},{"src":"l-ramakrishnan.jpg","title":"l-ramakrishnan"},{"src":"akshay-ananthapadmanabhan.jpg","title":"akshay-ananthapadmanabhan"},{"src":"k-v-gopalakrishnan.jpg","title":"k-v-gopalakrishnan"}],"songs":[{"name":"Era napai","ragam":"Todi","talam":"Adi","composer":"Patnam Subramanya Iyer"},{"name":"Shri nathadi Guruguho","ragam":"Mayamalavagowlai","talam":"Adi","composer":"Muthuswami Dikshithar"},{"name":"Shri Saraswathi Namosthuthe","ragam":"Arabhi","talam":"Rupakam","composer":"Muthuswami Dikshithar"},{"name":"Mahatmule","ragam":"Rishabapriya","talam":"Adi","composer":"Mysore Vasudevacharya"},{"name":"Kanakasaila","ragam":"Punnagavarali","talam":"Adi","composer":"Syama Sastry"},{"name":"Vitajaladhura","ragam":"Janaranjani","talam":"Adi","composer":"Thyagaraja"},{"name":"Geetharthamu","ragam":"Surati","talam":"Adi","composer":"Thyagaraja"},{"name":"(RTP) Pallavi Uma Rama Saraswathi","ragam":"Saraswathi followed by Ragamalika","talam":"Chatusra Jathi Rupakam"},{"name":"Rama Mantrava Japiso","ragam":"Jonpuri","talam":"Adi","composer":" Purandara Dasa"},{"name":"Sharada Bhujanga Stotram","ragam":"Ragamalika","talam":"Tisra Chapu","composer":"Adi Sankara"},{"name":"Nadanthal kalkai Nondavo","talam":"Adi","composer":"Thirumazhisai Alwar"},{"name":"Shree Kamalambike","ragam":"Sri","talam":"Khanda Jathi Eka","composer":"Muthuswami Dikshithar"}]}